vl16008uno/__init__.py
vl16008uno/demo.py
vl16008uno/metodos_lineales.py
vl16008uno/metodos_no_lineales.py
vl16008uno-0.1.1.dist-info/licenses/LICENSE
vl16008uno-0.1.1.dist-info/METADATA
vl16008uno-0.1.1.dist-info/WHEEL
vl16008uno-0.1.1.dist-info/entry_points.txt
vl16008uno-0.1.1.dist-info/top_level.txt
vl16008uno-0.1.1.dist-info/RECORD
